odoo/addons/pos_partner_location_google_map/README.rst
odoo/addons/pos_partner_location_google_map/__init__.py
odoo/addons/pos_partner_location_google_map/__manifest__.py
odoo/addons/pos_partner_location_google_map/i18n/it.po
odoo/addons/pos_partner_location_google_map/i18n/pos_partner_location_google_map.pot
odoo/addons/pos_partner_location_google_map/models/__init__.py
odoo/addons/pos_partner_location_google_map/models/address_google_struct.py
odoo/addons/pos_partner_location_google_map/models/base_geocoder.py
odoo/addons/pos_partner_location_google_map/models/pos_config.py
odoo/addons/pos_partner_location_google_map/models/res_partner.py
odoo/addons/pos_partner_location_google_map/readme/CONFIGURATION.rst
odoo/addons/pos_partner_location_google_map/readme/CONTRIBUTORS.rst
odoo/addons/pos_partner_location_google_map/readme/DESCRIPTION.rst
odoo/addons/pos_partner_location_google_map/readme/USAGE.rst
odoo/addons/pos_partner_location_google_map/static/description/icon.png
odoo/addons/pos_partner_location_google_map/static/description/index.html
odoo/addons/pos_partner_location_google_map/static/src/js/PartnerDetailsMapGoogleEdit.esm.js
odoo/addons/pos_partner_location_google_map/static/src/js/PartnerMapGoogleEdit.esm.js
odoo/addons/pos_partner_location_google_map/tests/__init__.py
odoo/addons/pos_partner_location_google_map/tests/common.py
odoo/addons/pos_partner_location_google_map/tests/test_address_google_struct.py
odoo/addons/pos_partner_location_google_map/tests/test_base_geocoder.py
odoo/addons/pos_partner_location_google_map/tests/test_res_partner.py
odoo_addon_pos_partner_location_google_map-16.0.1.0.1.dist-info/METADATA
odoo_addon_pos_partner_location_google_map-16.0.1.0.1.dist-info/WHEEL
odoo_addon_pos_partner_location_google_map-16.0.1.0.1.dist-info/top_level.txt
odoo_addon_pos_partner_location_google_map-16.0.1.0.1.dist-info/RECORD
